[
    {
        "id": "95d043e055f256a14c52e31e81142eb8503850e79c9bbe56c7ca4d4ece6c8bed",
        "title": "BOC commande 40 B737 MAX !",
        "description": "<p>LA SUITE : www.avianews.ch</p>",
        "pubDate": "",
        "link": "http://psk.blog.24heures.ch/archive/2022/12/28/boc-commande-40-b737-max-874006.html",
        "language": "en",
        "categorie": "BUSINESS",
        "data": "boc command 40 b737 max ! : avia news mesur d'audienc roi statistiqu webanalyt par avia news les nouvell de l'aviation, enqu\u00eates, comparaison newslett s'inscrir se d\u00e9sinscrir \u00e0 propo les lien sympathiqu & util achet un avion ? facil ! aviap :le top des site ! breitl superconstel ass. scfa campagn pro-avion de combat european feder histor aviation le site d'un super spotter ! david studer luxuri privat jet mus\u00e9 de l'aviat militaire, payern (clindailes) s\u00e9curit\u00e9 des vosl/observatoir ind\u00e9p. s\u00e9lection pilot de chass (sphair) suiss defens www.aerosuisse.ch d\u00e9cembr 2022 d l m m j v s 1 2 3 4 5 6 7 8 9 10 11 12 13 14 15 16 17 18 19 20 21 22 23 24 25 26 27 28 29 30 31 note r\u00e9cent boc command 40 b737 max ! premier a330-900 pour condor ! la colombi s\u00e9lectionn le rafal ! mise \u00e0 jour du simulateur du ncpc-7! l\u2019europ lanc l\u2019engrt ! le gripen e entr en servic au br\u00e9sil ! des brimston pour les eurofight espagnol ! berlin command le f-35 ! gross command de 200 avion pour boe ! swiss choisi l\u2019a350-900! commentair r\u00e9cent shaan sur la colombi s\u00e9lectionn le rafal ! mirco sur la colombi s\u00e9lectionn le rafal ! pk sur la colombi s\u00e9lectionn le rafal ! greg sur la colombi s\u00e9lectionn le rafal ! pk sur la colombi s\u00e9lectionn le rafal ! s\u00e9bastien sur la colombi s\u00e9lectionn le rafal ! edagar sur la colombi s\u00e9lectionn le rafal ! pk sur la colombi s\u00e9lectionn le rafal ! edgar sur la colombi s\u00e9lectionn le rafal ! yves sur la colombi s\u00e9lectionn le rafal ! cat\u00e9gori air2030 associat aviat aviation & tourism aviat et \u00e9cologi dca & aviat spatial archive 2022-12 2022-11 2022-10 2022-09 2022-08 2022-07 2022-06 2022-05 2022-04 2022-03 tout les archiv \u00ab premier a330-900 pour condor ! | page d'accueil 28/12/2022 boc command 40 b737 max ! la suite : www.avianews.ch 11:03 \u00e9crit par pascal dan aviat | lien perman | commentair (0) | facebook | | les commentair sont ferm\u00e9s."
    }
]